{"Valutes":[{"NameOfValute":"Fruit Coins","Values":[{"ValueName":"Basic ","Valute":0.0,"MultiOfValute":0.0},{"ValueName":"Thousen","Valute":0.0,"MultiOfValute":0.0},{"ValueName":"Million","Valute":0.0,"MultiOfValute":0.0},{"ValueName":"Billion","Valute":0.0,"MultiOfValute":0.0},{"ValueName":"Trillion","Valute":0.0,"MultiOfValute":0.0},{"ValueName":"Quadrillion","Valute":0.0,"MultiOfValute":0.0}],"TextsOfValute":[{"instanceID":17856}],"SybwolsOfValue":["","k","M","B","T","q"],"NumberOfValue":0,"NumberOfMulti":0},{"NameOfValute":"Fruit Dimonds","Values":[{"ValueName":"Basic ","Valute":0.0,"MultiOfValute":0.0},{"ValueName":"Thousen","Valute":0.0,"MultiOfValute":0.0},{"ValueName":"Million","Valute":0.0,"MultiOfValute":0.0},{"ValueName":"Billion","Valute":0.0,"MultiOfValute":0.0},{"ValueName":"Trillion","Valute":0.0,"MultiOfValute":0.0}],"TextsOfValute":[{"instanceID":17068}],"SybwolsOfValue":["","k","M","B","T"],"NumberOfValue":0,"NumberOfMulti":0},{"NameOfValute":"MultiFruit Coins","Values":[{"ValueName":"Basic ","Valute":0.0,"MultiOfValute":0.0},{"ValueName":"Thousen","Valute":0.0,"MultiOfValute":0.0},{"ValueName":"Million","Valute":0.0,"MultiOfValute":0.0},{"ValueName":"Billion","Valute":0.0,"MultiOfValute":0.0},{"ValueName":"Trillion","Valute":0.0,"MultiOfValute":0.0}],"TextsOfValute":[{"instanceID":18844}],"SybwolsOfValue":["","k","M","B","T"],"NumberOfValue":0,"NumberOfMulti":0}]}